setup.py
oython_test/__init__.py
oython_test/oython_test.py
oython_test.egg-info/PKG-INFO
oython_test.egg-info/SOURCES.txt
oython_test.egg-info/dependency_links.txt
oython_test.egg-info/top_level.txt