Metadata-Version: 2.1
Name: oython-test
Version: 0.0.1
Summary: oython库，作者:李承泽（正常线路下载失败时，请切换为python原版路线）。
Home-page: https://github.com/
Author: Chengze Li
Author-email: 3161399620@qq.com
License: UNKNOWN
Platform: UNKNOWN
Classifier: Programming Language :: Python :: 3
Classifier: License :: OSI Approved :: MIT License
Classifier: Operating System :: OS Independent
